esp32_deauth/__init__.py
esp32_deauth/cli.py
esp32_deauth/deauth.py
esp32_deauth/firmware/bootloader.bin
esp32_deauth/firmware/esp32-wifi-penetration-tool.bin
esp32_deauth/firmware/partition-table.bin
esp32_deauth-0.3.3.dist-info/licenses/LICENSE
esp32_deauth-0.3.3.dist-info/METADATA
esp32_deauth-0.3.3.dist-info/WHEEL
esp32_deauth-0.3.3.dist-info/entry_points.txt
esp32_deauth-0.3.3.dist-info/top_level.txt
esp32_deauth-0.3.3.dist-info/RECORD
