Metadata-Version: 2.4
Name: esp32-deauth
Version: 0.3.3
Summary: A Python tool for Wi-Fi deauthentication attacks using ESP32 with webserver firmware
Home-page: https://github.com/ishanoshada/esp32-deauth
Author: Ishan Oshada
Author-email: ishan.kodtihuwakku.officals@gmail.com
License: GPL-2.0
Project-URL: Documentation, https://github.com/ishanoshada/esp32-deauth#readme
Project-URL: Source, https://github.com/ishanoshada/esp32-deauth
Project-URL: Tracker, https://github.com/ishanoshada/esp32-deauth/issues
Keywords: esp32 wifi deauth deauthentication penetration security hacking
Classifier: Programming Language :: Python :: 3
Classifier: Programming Language :: Python :: 3.7
Classifier: Programming Language :: Python :: 3.8
Classifier: Programming Language :: Python :: 3.9
Classifier: Programming Language :: Python :: 3.10
Classifier: Programming Language :: Python :: 3.11
Classifier: License :: OSI Approved :: GNU General Public License v2 (GPLv2)
Classifier: Operating System :: Microsoft :: Windows
Classifier: Operating System :: POSIX :: Linux
Classifier: Operating System :: MacOS
Classifier: Intended Audience :: Information Technology
Classifier: Intended Audience :: Developers
Classifier: Topic :: Security
Classifier: Topic :: Software Development :: Libraries :: Python Modules
Classifier: Topic :: Utilities
Requires-Python: >=3.7
License-File: LICENSE
Requires-Dist: esptool>=4.9.0
Requires-Dist: requests>=2.28.0
Requires-Dist: tabulate>=0.9.0
Requires-Dist: click>=8.0
Requires-Dist: colorlog
Dynamic: author
Dynamic: author-email
Dynamic: classifier
Dynamic: description
Dynamic: description-content-type
Dynamic: home-page
Dynamic: keywords
Dynamic: license
Dynamic: license-file
Dynamic: project-url
Dynamic: requires-dist
Dynamic: requires-python
Dynamic: summary
